gensimplus-4.1.dist-info/DESCRIPTION.rst
gensimplus-4.1.dist-info/METADATA
gensimplus-4.1.dist-info/RECORD
gensimplus-4.1.dist-info/WHEEL
gensimplus-4.1.dist-info/metadata.json
gensimplus-4.1.dist-info/top_level.txt
source/__init__.py
source/base_interface.py
source/conf.py
source/dictionary_helper.py
source/gensim_plus_config.py
source/model_save_load_helper.py
source/reghelper.py
source/tfidf_helper.py
source/word2vec_helper.py
